[{"index": "Question_1", "timestamp": 55.12, "duration": 5.279, "question": "What is the largest man in the world?", "question_type": "Poll", "options": ["An elephant", "Blue whale", "Giraffe"]}, {"index": "Question_2", "timestamp": 80.64, "duration": 4.76, "question": "Which country has the second largest population in the world?", "question_type": "Poll", "options": ["China", "India", "The United States", "Brazil"]}, {"index": "Question_3", "timestamp": 97.36, "duration": 5.48, "question": "Which of the following animals is not a mammal?", "question_type": "Poll", "options": ["Dog", "Cat", "Bird", "Whale", "Dolphin", "Bat"]}, {"index": "Question_4", "timestamp": 120.88, "duration": 3.44, "question": "Which programming language is the best?", "question_type": "Open", "options": []}]